{
  "version": "1.0.0",
  "updated": "2026-06-24",
  "phases": [
    {
      "id": "phase-1",
      "name": "Core Gateway Infrastructure",
      "description": "GatewayManager, asyncio Queue, and BaseAdapter setup.",
      "icon": "gateway",
      "status": "DONE",
      "tasks": [
        {"id": "1.1", "name": "GatewayManager with asyncio.Queue", "status": "DONE", "description": "Central message bus."},
        {"id": "1.2", "name": "BaseAdapter ABC", "status": "DONE", "description": "Interface for platform adapters."},
        {"id": "1.3", "name": "Universal Message Format", "status": "DONE", "description": "Normalized Message dataclass."},
        {"id": "1.4", "name": "Singleton GatewayManager", "status": "DONE", "description": "Global gateway instance."},
        {"id": "1.5", "name": "Gateway Monitor UI", "status": "DONE", "description": "Dashboard with status, queue log, toggles."}
      ]
    },
    {
      "id": "phase-2",
      "name": "Telegram Polling Adapter",
      "description": "Stable, headless Telegram integration — no tunnels, no webhooks.",
      "icon": "telegram",
      "status": "DONE",
      "tasks": [
        {"id": "2.1", "name": "getUpdates long-polling", "status": "DONE", "description": "Background task polling every 1s."},
        {"id": "2.2", "name": "Message normalization", "status": "DONE", "description": "Telegram update → UMF Message."},
        {"id": "2.3", "name": "send() outbound routing", "status": "DONE", "description": "sendMessage API integration."},
        {"id": "2.4", "name": "Connectivity check on start", "status": "DONE", "description": "getMe validation before polling."}
      ]
    },
    {
      "id": "phase-3",
      "name": "Unified Agent Logic (Queue Consumer)",
      "description": "The agent brain consumes from the gateway queue — completely platform agnostic.",
      "icon": "brain",
      "status": "DONE",
      "tasks": [
        {"id": "3.1", "name": "Gateway consumer background task", "status": "DONE", "description": "asyncio task: queue → agent.run() → reply."},
        {"id": "3.2", "name": "MessageDispatcher reply contract", "status": "DONE", "description": "reply(sender_id, content) routes by platform prefix."},
        {"id": "3.3", "name": "Session mapping via sender_id", "status": "DONE", "description": "sender_id → thread_id for conversation continuity."},
        {"id": "3.4", "name": "Deprecate kazma-comms webhooks", "status": "DONE", "description": "Removed webhook-based telegram_bridge."},
        {"id": "3.5", "name": "send_message ReAct tool", "status": "DONE", "description": "Agent calls send_message(sender_id, content) — platform agnostic."}
      ]
    },
    {
      "id": "phase-4",
      "name": "Expansion (Discord / WhatsApp)",
      "description": "New platform adapters using BaseAdapter.",
      "icon": "expand",
      "status": "IN_PROGRESS",
      "tasks": [
        {"id": "4.1", "name": "Discord adapter", "status": "TODO", "description": "Discord.py-based gateway bot."},
        {"id": "4.2", "name": "WhatsApp adapter", "status": "TODO", "description": "WhatsApp Business API webhook."},
        {"id": "4.3", "name": "Slack adapter (Socket Mode)", "status": "TODO", "description": "No public URL needed."},
        {"id": "4.4", "name": "Adapter auto-discovery", "status": "TODO", "description": "Scan kazma.yaml for enabled adapters."}
      ]
    }
  ]
}
